MANIFEST.in
README.md
setup.py
CKReportPortal.egg-info/PKG-INFO
CKReportPortal.egg-info/SOURCES.txt
CKReportPortal.egg-info/dependency_links.txt
CKReportPortal.egg-info/requires.txt
CKReportPortal.egg-info/top_level.txt
src/CKReportPortal/__init__.py