Metadata-Version: 1.0
Name: CKReportPortal
Version: 0.0.1b3
Summary: ChokChaisak
Home-page: https://github.com/ChokChaisak/ChokChaisak
Author: ChokChaisak
Author-email: ChokChaisak@gmail.com
License: ChokChaisak
Keywords: CKReportPortal
Platform: UNKNOWN
